repello_artemis_sdk/__init__.py
repello_artemis_sdk/client.py
repello_artemis_sdk/api/__init__.py
repello_artemis_sdk/api/assets_api.py
repello_artemis_sdk/api/orgs_api.py
repello_artemis_sdk/api/users_api.py
repello_artemis_sdk/base/__init__.py
repello_artemis_sdk/base/api_base.py
repello_artemis_sdk/enums/__init__.py
repello_artemis_sdk/enums/scan_types.py
repello_artemis_sdk/error/__init__.py
repello_artemis_sdk/error/errors.py
repello_artemis_sdk/utils/__init__.py
repello_artemis_sdk/utils/endpoints.py
repello_artemis_sdk/utils/loggers.py
repello_artemis_sdk/utils/requests.py
repello_artemis_sdk-1.0.2.dist-info/LICENSE
repello_artemis_sdk-1.0.2.dist-info/METADATA
repello_artemis_sdk-1.0.2.dist-info/WHEEL
repello_artemis_sdk-1.0.2.dist-info/top_level.txt
repello_artemis_sdk-1.0.2.dist-info/RECORD
