Metadata-Version: 2.2
Name: repello-artemis-sdk
Version: 1.0.2
Summary: Client SDK for triggering actions on Repello's Artemis Platform
Author-email: Aryan Ranjan <aryan@repello.ai>
License: Apache-2.0
Project-URL: Homepage, https://github.com/Repello-AI/repello-artemis-sdk
Project-URL: Bug Tracker, https://github.com/Repello-AI/repello-artemis-sdk/issues
Classifier: Programming Language :: Python :: 3
Classifier: License :: OSI Approved :: Apache Software License
Classifier: Operating System :: OS Independent
Requires-Python: >=3.10
License-File: LICENSE
Requires-Dist: requests>=2.25.0
Provides-Extra: dev
Requires-Dist: pytest>=7.0.0; extra == "dev"
Requires-Dist: pytest-cov>=4.0.0; extra == "dev"
Requires-Dist: black>=23.0.0; extra == "dev"
